reviewminer/__init__.py
reviewminer/aspect_opinion.py
reviewminer/basic.py
reviewminer/core.py
reviewminer/sentiment.py
reviewminer-1.0.0.3.dist-info/LICENSE
reviewminer-1.0.0.3.dist-info/METADATA
reviewminer-1.0.0.3.dist-info/WHEEL
reviewminer-1.0.0.3.dist-info/top_level.txt
reviewminer-1.0.0.3.dist-info/RECORD
