Metadata-Version: 2.1
Name: reviewminer
Version: 1.0.0.3
Summary: Comprehensive text analysis on customers reviews data
Home-page: https://github.com/tianyiwangnova/2021_project__ReviewMiner
Author: Tianyi Wang
Author-email: tw2567@columbia.edu
License: UNKNOWN
Project-URL: Documentation, https://github.com/tianyiwangnova/2021_project__ReviewMiner/wiki/Documentation
Project-URL: Source Code, https://github.com/tianyiwangnova/2021_project__ReviewMiner
Project-URL: Knowledge Center, https://github.com/tianyiwangnova/2021_project__ReviewMiner/wiki/Knowledge-Center
Platform: UNKNOWN
Classifier: License :: OSI Approved :: MIT License
Classifier: Programming Language :: Python :: 3
Classifier: Programming Language :: Python :: 3.7
Requires-Dist: pandas
Requires-Dist: textblob
Requires-Dist: nltk
Requires-Dist: datetime
Requires-Dist: seaborn
Requires-Dist: plotly
Requires-Dist: codecov
Requires-Dist: pytest
Requires-Dist: pytest-cov
Requires-Dist: pytest-mpl
